interiutIII_blackdoor/__init__.py
interiutIII_blackdoor/blackdoor.py
Inter_IUT_3_Blackdoor-6.6.6.dist-info/.SOURCES.txt.~682b
Inter_IUT_3_Blackdoor-6.6.6.dist-info/METADATA
Inter_IUT_3_Blackdoor-6.6.6.dist-info/WHEEL
Inter_IUT_3_Blackdoor-6.6.6.dist-info/top_level.txt
Inter_IUT_3_Blackdoor-6.6.6.dist-info/RECORD
