Metadata-Version: 2.1
Name: Inter-IUT-3-Blackdoor
Version: 6.6.6
Summary: Just backdooring some computer ...
Home-page: https://0xswitch.fr
Author: switch
License: WTFPL
Platform: UNKNOWN
Requires-Python: >=3
